Metadata-Version: 2.1
Name: chAMReDb
Version: 0.2.1
Summary: Package to find the equivalent antibiotic resistance genes (ARGs) in other databases based on ARG(s) from one AMR determinant database
Home-page: UNKNOWN
Author: Anthony Underwood
Author-email: anthony.underwood@cgps.group
License: MIT
Platform: UNKNOWN
Classifier: Development Status :: 4 - Beta
Classifier: Intended Audience :: Science/Research
Classifier: License :: OSI Approved :: MIT License
Classifier: Programming Language :: Python :: 3
Requires-Dist: networkx
Requires-Dist: pronto
Requires-Dist: rich
Requires-Dist: pandas
Requires-Dist: seaborn
Requires-Dist: numpy
